drona/__init__.py
drona/data_science_df_clean.csv
drona/data_science_df_pictures.csv
drona-13.0.0.dist-info/LICENSE.txt
drona-13.0.0.dist-info/METADATA
drona-13.0.0.dist-info/WHEEL
drona-13.0.0.dist-info/top_level.txt
drona-13.0.0.dist-info/RECORD
