Metadata-Version: 2.1
Name: drona
Version: 13.0.0
Summary: This is a data science related question asnwering model for the beginners
Home-page: 
Author: Prabir Debnath
Author-email: prabirdeb@gmail.com
License: MIT
Keywords: data science,datascience,machine learning,deep learning
License-File: LICENSE.txt
Requires-Dist: numpy (==1.21.5)
Requires-Dist: pandas (==1.3.5)
Requires-Dist: nltk (==3.2.5)
Requires-Dist: scikit-learn (==1.0.2)
